CHANGES.txt
README.txt
bootstrap.py
buildout.cfg
setup.py
src/zope/__init__.py
src/zope.app.pythonpage.egg-info/PKG-INFO
src/zope.app.pythonpage.egg-info/SOURCES.txt
src/zope.app.pythonpage.egg-info/dependency_links.txt
src/zope.app.pythonpage.egg-info/namespace_packages.txt
src/zope.app.pythonpage.egg-info/not-zip-safe
src/zope.app.pythonpage.egg-info/requires.txt
src/zope.app.pythonpage.egg-info/top_level.txt
src/zope/app/__init__.py
src/zope/app/pythonpage/MAINTAINER.txt
src/zope/app/pythonpage/README.txt
src/zope/app/pythonpage/SETUP.cfg
src/zope/app/pythonpage/__init__.py
src/zope/app/pythonpage/browser.py
src/zope/app/pythonpage/configure.zcml
src/zope/app/pythonpage/edit.pt
src/zope/app/pythonpage/pythonpage-configure.zcml
src/zope/app/pythonpage/tests.py
src/zope/app/pythonpage/version.txt